[
  { "tenant_id": 1, "name": "All", "description": "Global poller and remediation executor", "enabled": true, "trigger_type": "AUTHMIND_POLL", "min_severity": "Low" },
  { "tenant_id": 1, "name": "Compromised User", "description": "Remediation for compromised accounts", "enabled": true, "trigger_type": "AUTHMIND_POLL", "min_severity": "Low" },
  { "tenant_id": 1, "name": "Access from Anonymous IP", "enabled": false, "trigger_type": "AUTHMIND_POLL", "min_severity": "Low" },
  { "tenant_id": 1, "name": "Access from Public VPN", "enabled": false, "trigger_type": "AUTHMIND_POLL", "min_severity": "Low" },
  { "tenant_id": 1, "name": "Access from Unauthorized Countries", "enabled": false, "trigger_type": "AUTHMIND_POLL", "min_severity": "Low" },
  { "tenant_id": 1, "name": "Access to Anonymous IP", "enabled": false, "trigger_type": "AUTHMIND_POLL", "min_severity": "Low" },
  { "tenant_id": 1, "name": "Access to Public VPN", "enabled": false, "trigger_type": "AUTHMIND_POLL", "min_severity": "Low" },
  { "tenant_id": 1, "name": "Access to Unauthorized Countries", "enabled": false, "trigger_type": "AUTHMIND_POLL", "min_severity": "Low" },
  { "tenant_id": 1, "name": "Auth Hash Quality", "enabled": false, "trigger_type": "AUTHMIND_POLL", "min_severity": "Low" },
  { "tenant_id": 1, "name": "Auth Hash Security", "enabled": false, "trigger_type": "AUTHMIND_POLL", "min_severity": "Low" },
  { "tenant_id": 1, "name": "Auth Protocol Quality", "enabled": false, "trigger_type": "AUTHMIND_POLL", "min_severity": "Low" },
  { "tenant_id": 1, "name": "Compromised Password", "enabled": false, "trigger_type": "AUTHMIND_POLL", "min_severity": "Low" },
  { "tenant_id": 1, "name": "Deviation in Daily Asset Activity", "enabled": false, "trigger_type": "AUTHMIND_POLL", "min_severity": "Low" },
  { "tenant_id": 1, "name": "Enumeration of AD Admins", "enabled": false, "trigger_type": "AUTHMIND_POLL", "min_severity": "Low" },
  { "tenant_id": 1, "name": "Enumeration of AD Users", "enabled": false, "trigger_type": "AUTHMIND_POLL", "min_severity": "Low" },
  { "tenant_id": 1, "name": "Exposed Assets", "enabled": false, "trigger_type": "AUTHMIND_POLL", "min_severity": "Low" },
  { "tenant_id": 1, "name": "Lack of MFA", "enabled": false, "trigger_type": "AUTHMIND_POLL", "min_severity": "Low" },
  { "tenant_id": 1, "name": "Identity No MFA", "enabled": false, "trigger_type": "AUTHMIND_POLL", "min_severity": "Low" },
  { "tenant_id": 1, "name": "Asset No MFA", "enabled": false, "trigger_type": "AUTHMIND_POLL", "min_severity": "Low" },
  { "tenant_id": 1, "name": "Repeated AD Login Attempts at Invalid Time", "enabled": false, "trigger_type": "AUTHMIND_POLL", "min_severity": "Low" },
  { "tenant_id": 1, "name": "Repeated Login Attempts at Invalid Device", "enabled": false, "trigger_type": "AUTHMIND_POLL", "min_severity": "Low" },
  { "tenant_id": 1, "name": "Shadow Access", "enabled": false, "trigger_type": "AUTHMIND_POLL", "min_severity": "Low" },
  { "tenant_id": 1, "name": "Shadow Assets", "enabled": false, "trigger_type": "AUTHMIND_POLL", "min_severity": "Low" },
  { "tenant_id": 1, "name": "Shadow Identity Systems", "enabled": false, "trigger_type": "AUTHMIND_POLL", "min_severity": "Low" },
  { "tenant_id": 1, "name": "Suspected AD NTLM Relay Attack", "enabled": false, "trigger_type": "AUTHMIND_POLL", "min_severity": "Low" },
  { "tenant_id": 1, "name": "Suspected Attack on Disabled AD Account", "enabled": false, "trigger_type": "AUTHMIND_POLL", "min_severity": "Low" },
  { "tenant_id": 1, "name": "Suspected Attack on Expired AD Account", "enabled": false, "trigger_type": "AUTHMIND_POLL", "min_severity": "Low" },
  { "tenant_id": 1, "name": "Suspected Attack on Locked AD Account", "enabled": false, "trigger_type": "AUTHMIND_POLL", "min_severity": "Low" },
  { "tenant_id": 1, "name": "Suspected AD Brute-force Attack", "enabled": false, "trigger_type": "AUTHMIND_POLL", "min_severity": "Low" },
  { "tenant_id": 1, "name": "Suspected Identity Brute-force Attack", "enabled": false, "trigger_type": "AUTHMIND_POLL", "min_severity": "Low" },
  { "tenant_id": 1, "name": "Suspected Directory/IdP Bot Attack", "enabled": false, "trigger_type": "AUTHMIND_POLL", "min_severity": "Low" },
  { "tenant_id": 1, "name": "Suspected Directory/IdP Password Spray Attack", "enabled": false, "trigger_type": "AUTHMIND_POLL", "min_severity": "Low" },
  { "tenant_id": 1, "name": "Suspicious Inbound Access", "enabled": false, "trigger_type": "AUTHMIND_POLL", "min_severity": "Low" },
  { "tenant_id": 1, "name": "Suspicious Outbound Access", "enabled": false, "trigger_type": "AUTHMIND_POLL", "min_severity": "Low" },
  { "tenant_id": 1, "name": "Unauthorized Asset Access", "enabled": false, "trigger_type": "AUTHMIND_POLL", "min_severity": "Low" },
  { "tenant_id": 1, "name": "Unknown SaaS Access", "enabled": false, "trigger_type": "AUTHMIND_POLL", "min_severity": "Low" },
  { "tenant_id": 1, "name": "Weak Password", "enabled": false, "trigger_type": "AUTHMIND_POLL", "min_severity": "Low" },
  { "tenant_id": 1, "name": "Unauthorized Identity Access", "enabled": false, "trigger_type": "AUTHMIND_POLL", "min_severity": "Low" },
  { "tenant_id": 1, "name": "Impossible Travel", "enabled": false, "trigger_type": "AUTHMIND_POLL", "min_severity": "Low" },
  { "tenant_id": 1, "name": "Suspected Access Token Sharing", "enabled": false, "trigger_type": "AUTHMIND_POLL", "min_severity": "Low" }
]
